hmorse/__init__.py
hmorse/__main__.py
hmorse-1.2.1.dist-info/WHEEL
hmorse-1.2.1.dist-info/METADATA
hmorse-1.2.1.dist-info/RECORD
